gcskewer/__init__.py
gcskewer/checks.py
gcskewer/io.py
gcskewer/main.py
gcskewer/parser.py
gcskewer-1.0.0.dist-info/LICENSE
gcskewer-1.0.0.dist-info/METADATA
gcskewer-1.0.0.dist-info/WHEEL
gcskewer-1.0.0.dist-info/entry_points.txt
gcskewer-1.0.0.dist-info/top_level.txt
gcskewer-1.0.0.dist-info/RECORD
