Metadata-Version: 2.1
Name: gcskewer
Version: 1.0.0
Summary: A python for plotting GC-skew from DNA sequences.
Home-page: https://github.com/DrBoothTJ/gcskewer
Author: Thomas J. Booth
Author-email: thoboo@biosustain.dtu.dk
License: GNU General Public License v3.0
Requires-Python: >=3.7
License-File: LICENSE
Requires-Dist: Bio
Requires-Dist: matplotlib
Requires-Dist: plotly
